setup.py
test1/function.py
wanwei_test.egg-info/PKG-INFO
wanwei_test.egg-info/SOURCES.txt
wanwei_test.egg-info/dependency_links.txt
wanwei_test.egg-info/top_level.txt