Metadata-Version: 1.0
Name: wanwei-test
Version: 0.0.1
Summary: health checker for MySQL database
Home-page: https://github.com/wanwei890116/test
Author: Wanwei
Author-email: 784971886@qq.com
License: UNKNOWN
Platform: UNKNOWN
